luckywood/__init__.py
luckywood/async_http_call.py
luckywood/data_caching.py
luckywood/database.py
luckywood/string.py
luckywood/chalice_blueprints/__init__.py
luckywood/chalice_blueprints/data_caching.py
luckywood-0.6.2.dist-info/LICENSE
luckywood-0.6.2.dist-info/METADATA
luckywood-0.6.2.dist-info/WHEEL
luckywood-0.6.2.dist-info/top_level.txt
luckywood-0.6.2.dist-info/RECORD
