Metadata-Version: 2.1
Name: luckywood
Version: 0.6.2
Summary: Package of helper classes.
Home-page: https://github.com/gluecks-gmbh/luckywood
Download-URL: https://pypi.org/project/luckywood/
Author: Frederik Glücks, Christian Wald-von der Lahr
Author-email: frederik@gluecks-gmbh.de, christian@waldvonderlahr-it.de
License: LGPL-3.0
Requires-Python: >=3.8
License-File: LICENSE
Requires-Dist: mysql-connector-python ~=8.3.0
Requires-Dist: requests ~=2.31.0
Requires-Dist: boto3 ~=1.34.66
